<bindings xmlns:wsdl="http://schemas.xmlsoap.org/wsdl/"
  xmlns:xs="http://www.w3.org/2001/XMLSchema"
  xmlns:jxb="http://java.sun.com/xml/ns/jaxb"
  wsdlLocation="FieldWorkAppointmentService_v3_0.wsdl"
  xmlns="http://java.sun.com/xml/ns/jaxws">
	<enableWrapperStyle>false</enableWrapperStyle>	
	<bindings node="wsdl:definitions/wsdl:portType[@name='FieldWorkAppointmentService_v3_0_PortType']">
	        <class name="FieldWorkAppointmentServicePortType"/> 
	</bindings>
	<bindings node="wsdl:definitions/wsdl:service[@name='FieldWorkAppointmentService_v3_0']">
		    <class name="FieldWorkAppointmentServiceStub"/> 
	</bindings>
</bindings>
